pydv/__init__.py
pydv/crc.py
pydv/dextra.py
pydv/dstar.py
pydv/dvtool.py
pydv/network.py
pydv/player.py
pydv/recorder.py
pydv/stream.py
pydv/utils.py
pydv-0.1.dist-info/LICENSE
pydv-0.1.dist-info/METADATA
pydv-0.1.dist-info/WHEEL
pydv-0.1.dist-info/entry_points.txt
pydv-0.1.dist-info/top_level.txt
pydv-0.1.dist-info/RECORD
